sick_scan_tcp/__init__.py
sick_scan_tcp/sick_scan_tcp.py
sick_scan_tcp-1.0.1.dist-info/METADATA
sick_scan_tcp-1.0.1.dist-info/WHEEL
sick_scan_tcp-1.0.1.dist-info/top_level.txt
sick_scan_tcp-1.0.1.dist-info/RECORD
