Metadata-Version: 2.1
Name: sick-scan-tcp
Version: 1.0.1
Summary: Library for interacting with SICK LIDAR sensors with TCP Connection
Home-page: https://github.com/Alimustoofaa/sick_scan
Author: Ali Mustofa
Author-email: hai.alimustofa@gmail.com
Keywords: Sick Scan,Sick Lidar,LMS511,LMS111
Classifier: Programming Language :: Python :: 3
Classifier: License :: OSI Approved :: MIT License
Classifier: Operating System :: OS Independent
